{
  "$schema": "https://schema.management.azure.com/schemas/2019-04-01/deploymentTemplate.json#",
  "contentVersion": "1.0.0.0",
  "metadata": {
    "_generator": {
      "name": "AzOps"
    }
  },
  "parameters": {},
  "variables": {},
  "resources": [
    {
      "type": "Microsoft.Compute/virtualMachines",
      "name": "dns-resolver-01",
      "apiVersion": "2022-03-01",
      "location": "westeurope",
      "tags": null,
      "properties": {
        "vmId": "6cda0ad9-1ef2-4b34-9bb6-f0b74986e332",
        "hardwareProfile": {
          "vmSize": "Standard_D2s_v3"
        },
        "storageProfile": {
          "imageReference": {
            "publisher": "canonical",
            "offer": "0001-com-ubuntu-server-focal",
            "sku": "20_04-lts-gen2",
            "version": "latest",
            "exactVersion": "20.04.202201180"
          },
          "osDisk": {
            "osType": "Linux",
            "name": "dns-resolver-01_disk1_bc66450b63184159a7eae57a89d055f7",
            "createOption": "FromImage",
            "caching": "ReadWrite",
            "managedDisk": {
              "storageAccountType": "Premium_LRS",
              "id": "/subscriptions/539e250b-b64b-4aec-aace-271141f578e5/resourceGroups/dns-resolver/providers/Microsoft.Compute/disks/dns-resolver-01_disk1_bc66450b63184159a7eae57a89d055f7"
            },
            "deleteOption": "Detach",
            "diskSizeGB": 30
          },
          "dataDisks": []
        },
        "osProfile": {
          "computerName": "dns-resolver-01",
          "adminUsername": "alwayson",
          "linuxConfiguration": {
            "disablePasswordAuthentication": false,
            "provisionVMAgent": true,
            "patchSettings": {
              "patchMode": "ImageDefault",
              "assessmentMode": "ImageDefault"
            }
          },
          "secrets": [],
          "allowExtensionOperations": true,
          "requireGuestProvisionSignal": true
        },
        "networkProfile": {
          "networkInterfaces": [
            {
              "id": "/subscriptions/539e250b-b64b-4aec-aace-271141f578e5/resourceGroups/dns-resolver/providers/Microsoft.Network/networkInterfaces/dns-resolver-0155"
            }
          ]
        },
        "diagnosticsProfile": {
          "bootDiagnostics": {
            "enabled": true
          }
        }
      }
    }
  ],
  "outputs": {}
}
