{
  "$schema": "https://schema.management.azure.com/schemas/2019-04-01/deploymentTemplate.json#",
  "contentVersion": "1.0.0.0",
  "metadata": {
    "_generator": {
      "name": "AzOps"
    }
  },
  "parameters": {},
  "variables": {},
  "resources": [
    {
      "type": "Microsoft.Authorization/roleAssignments",
      "name": "d19f2023-5b56-504d-b370-0f46bfd9e508",
      "apiVersion": "2022-01-01-preview",
      "properties": {
        "DisplayName": "Deploy-Private-DNS-Zones",
        "ObjectType": "ServicePrincipal",
        "PrincipalId": "d36008d3-f7cb-4af6-beb8-91323d2dfb28",
        "RoleDefinitionId": "/providers/Microsoft.Authorization/RoleDefinitions/4d97b98b-1d4f-4787-a291-c67834d212e7",
        "RoleDefinitionName": "Network Contributor"
      }
    }
  ],
  "outputs": {}
}
