{
  "$schema": "https://schema.management.azure.com/schemas/2019-04-01/deploymentTemplate.json#",
  "contentVersion": "1.0.0.0",
  "metadata": {
    "_generator": {
      "name": "AzOps"
    }
  },
  "parameters": {},
  "variables": {},
  "resources": [
    {
      "type": "Microsoft.Network/virtualNetworks/virtualNetworkPeerings",
      "apiVersion": "2020-11-01",
      "name": "AfO-hub-westeurope/ToSpoke-2",
      "properties": {
        "peeringState": "Connected",
        "remoteVirtualNetwork": {
          "id": "/subscriptions/afffa704-8cbd-46f2-a146-b473f632ecb5/resourceGroups/ao-network/providers/Microsoft.Network/virtualNetworks/vnet-we-2"
        },
        "allowVirtualNetworkAccess": true,
        "allowForwardedTraffic": true,
        "allowGatewayTransit": false,
        "useRemoteGateways": false,
        "remoteAddressSpace": {
          "addressPrefixes": [
            "192.168.16.0/20"
          ]
        }
      }
    }
  ],
  "outputs": {}
}
